CHANGELOG.md
MANIFEST.in
README.md
setup.py
iparapheur_utils.branches.egg-info/PKG-INFO
iparapheur_utils.branches.egg-info/SOURCES.txt
iparapheur_utils.branches.egg-info/dependency_links.txt
iparapheur_utils.branches.egg-info/entry_points.txt
iparapheur_utils.branches.egg-info/requires.txt
iparapheur_utils.branches.egg-info/top_level.txt
parapheur/__init__.py
parapheur/core.py
parapheur/script.cfg
parapheur/configs/export.cfg
parapheur/configs/import.cfg
parapheur/configs/pushdoc.cfg
parapheur/configs/recuparchives.cfg
parapheur/configs/script.cfg
parapheur/files/private.pem
parapheur/files/public.pem
parapheur/parapheur/Client.py
parapheur/parapheur/JSONHelper.py
parapheur/parapheur/Webservice.py
parapheur/parapheur/__init__.py
parapheur/parapheur/pprint.py
parapheur/scripts/__init__.py
parapheur/scripts/change_name.py
parapheur/scripts/checkInstallationIP.py
parapheur/scripts/export_data.py
parapheur/scripts/import_data.py
parapheur/scripts/pushdoc.py
parapheur/scripts/recupArchives.py
parapheur/scripts/remove_ldap.py
parapheur/scripts/javascript/removeNode.js
parapheur/scripts/shell/properties-merger/properties-merger.sh
parapheur/scripts/shell/properties-merger/unittests/unittests.sh